<?xml version="1.0" encoding="utf-8"?>
<fmg>
<compression>None</compression>
<version>DarkSouls1</version>
<bigendian>False</bigendian>
<entries>
<text id="74302000">Well, we meet again! What you doing here?</text>
<text id="74302001">%null%</text>
<text id="74302002">%null%</text>
<text id="74302003">%null%</text>
<text id="74302004">%null%</text>
<text id="74302005">%null%</text>
<text id="74302006">%null%</text>
<text id="74302007">%null%</text>
<text id="74302008">%null%</text>
<text id="74302009">%null%</text>
<text id="74302010">Who'dve thought we'd meet in a place like this.</text>
<text id="74302011">%null%</text>
<text id="74302012">%null%</text>
<text id="74302013">%null%</text>
<text id="74302014">%null%</text>
<text id="74302015">%null%</text>
<text id="74302016">%null%</text>
<text id="74302017">%null%</text>
<text id="74302018">%null%</text>
<text id="74302019">%null%</text>
<text id="74302020">Fate just won't let us stay apart, will she? Gah hah hah hah hah hah!</text>
<text id="74302100">See the old sword's caught your attention?
Well, you've a good eye, then.</text>
<text id="74302101">%null%</text>
<text id="74302102">%null%</text>
<text id="74302103">%null%</text>
<text id="74302104">%null%</text>
<text id="74302105">%null%</text>
<text id="74302106">%null%</text>
<text id="74302107">%null%</text>
<text id="74302108">%null%</text>
<text id="74302109">%null%</text>
<text id="74302110">Ah, it's been in my family for generations.</text>
<text id="74302111">%null%</text>
<text id="74302112">%null%</text>
<text id="74302113">%null%</text>
<text id="74302114">%null%</text>
<text id="74302115">%null%</text>
<text id="74302116">%null%</text>
<text id="74302117">%null%</text>
<text id="74302118">%null%</text>
<text id="74302119">%null%</text>
<text id="74302120">They say it is crafted with moonlight,
and we all know what that means, it wards off evil.</text>
<text id="74302121">%null%</text>
<text id="74302122">%null%</text>
<text id="74302123">%null%</text>
<text id="74302124">%null%</text>
<text id="74302125">%null%</text>
<text id="74302126">%null%</text>
<text id="74302127">%null%</text>
<text id="74302128">%null%</text>
<text id="74302129">%null%</text>
<text id="74302130">And I would nae trade her for all the riches in the world.</text>
<text id="74302131">%null%</text>
<text id="74302132">%null%</text>
<text id="74302133">%null%</text>
<text id="74302134">%null%</text>
<text id="74302135">%null%</text>
<text id="74302136">%null%</text>
<text id="74302137">%null%</text>
<text id="74302138">%null%</text>
<text id="74302139">%null%</text>
<text id="74302140">They say that no man has ever
teased oot the sword's true power.</text>
<text id="74302141">%null%</text>
<text id="74302142">%null%</text>
<text id="74302143">%null%</text>
<text id="74302144">%null%</text>
<text id="74302145">%null%</text>
<text id="74302146">%null%</text>
<text id="74302147">%null%</text>
<text id="74302148">%null%</text>
<text id="74302149">%null%</text>
<text id="74302150">But in the right hands... Heh heh heh heh heh heh...</text>
<text id="74302200">I see you've taken a liking to the sword.
Well, I applaud you, for you've a sharp eye.</text>
<text id="74302201">%null%</text>
<text id="74302202">%null%</text>
<text id="74302203">%null%</text>
<text id="74302204">%null%</text>
<text id="74302205">%null%</text>
<text id="74302206">%null%</text>
<text id="74302207">%null%</text>
<text id="74302208">%null%</text>
<text id="74302209">%null%</text>
<text id="74302210">But this is one sword pal
that I will nae be giving up.</text>
<text id="74302211">%null%</text>
<text id="74302212">%null%</text>
<text id="74302213">%null%</text>
<text id="74302214">%null%</text>
<text id="74302215">%null%</text>
<text id="74302216">%null%</text>
<text id="74302217">%null%</text>
<text id="74302218">%null%</text>
<text id="74302219">%null%</text>
<text id="74302220">If you still insist on having it...</text>
<text id="74302221">%null%</text>
<text id="74302222">%null%</text>
<text id="74302223">%null%</text>
<text id="74302224">%null%</text>
<text id="74302225">%null%</text>
<text id="74302226">%null%</text>
<text id="74302227">%null%</text>
<text id="74302228">%null%</text>
<text id="74302229">%null%</text>
<text id="74302230">Then you will have to pry it from my cold hands! Gah hah hah hah hah hah!</text>
<text id="74302300">I've a great debt to you.
And I'll never forget it.</text>
<text id="74302301">%null%</text>
<text id="74302302">%null%</text>
<text id="74302303">%null%</text>
<text id="74302304">%null%</text>
<text id="74302305">%null%</text>
<text id="74302306">%null%</text>
<text id="74302307">%null%</text>
<text id="74302308">%null%</text>
<text id="74302309">%null%</text>
<text id="74302310">I, Benhart, swear by my honour,
to aid you in your darkest hour! So nae problem pal.</text>
<text id="74305000">Very well. I, Benhart,
will be honoured to chop you to pieces.</text>
<text id="74305001">%null%</text>
<text id="74305002">%null%</text>
<text id="74305003">%null%</text>
<text id="74305004">%null%</text>
<text id="74305005">%null%</text>
<text id="74305006">%null%</text>
<text id="74305007">%null%</text>
<text id="74305008">%null%</text>
<text id="74305009">%null%</text>
<text id="74305010">You're a sorry waste of life...</text>
<text id="74305011">%null%</text>
<text id="74305012">%null%</text>
<text id="74305013">%null%</text>
<text id="74305014">%null%</text>
<text id="74305015">%null%</text>
<text id="74305016">%null%</text>
<text id="74305017">%null%</text>
<text id="74305018">%null%</text>
<text id="74305019">%null%</text>
<text id="74305020">You knew this would happen...</text>
<text id="74305021">%null%</text>
<text id="74305022">%null%</text>
<text id="74305023">%null%</text>
<text id="74305024">%null%</text>
<text id="74305025">%null%</text>
<text id="74305026">%null%</text>
<text id="74305027">%null%</text>
<text id="74305028">%null%</text>
<text id="74305029">%null%</text>
<text id="74305030">Ooph!</text>
<text id="74305031">%null%</text>
<text id="74305032">%null%</text>
<text id="74305033">%null%</text>
<text id="74305034">%null%</text>
<text id="74305035">%null%</text>
<text id="74305036">%null%</text>
<text id="74305037">%null%</text>
<text id="74305038">%null%</text>
<text id="74305039">%null%</text>
<text id="74305040">Enough with that!</text>
<text id="74305041">%null%</text>
<text id="74305042">%null%</text>
<text id="74305043">%null%</text>
<text id="74305044">%null%</text>
<text id="74305045">%null%</text>
<text id="74305046">%null%</text>
<text id="74305047">%null%</text>
<text id="74305048">%null%</text>
<text id="74305049">%null%</text>
<text id="74305050">What in bloody...!</text>
<text id="74305051">%null%</text>
<text id="74305052">%null%</text>
<text id="74305053">%null%</text>
<text id="74305054">%null%</text>
<text id="74305055">%null%</text>
<text id="74305056">%null%</text>
<text id="74305057">%null%</text>
<text id="74305058">%null%</text>
<text id="74305059">%null%</text>
<text id="74305060">Hey! How dare you!</text>
<text id="74305061">%null%</text>
<text id="74305062">%null%</text>
<text id="74305063">%null%</text>
<text id="74305064">%null%</text>
<text id="74305065">%null%</text>
<text id="74305066">%null%</text>
<text id="74305067">%null%</text>
<text id="74305068">%null%</text>
<text id="74305069">%null%</text>
<text id="74305070">What's done...urgh... Is done...</text>
<text id="74306000">A man's journey...is never done...</text>
<text id="74307000">We have outwitted death a good many times.</text>
<text id="74307001">%null%</text>
<text id="74307002">%null%</text>
<text id="74307003">%null%</text>
<text id="74307004">%null%</text>
<text id="74307005">%null%</text>
<text id="74307006">%null%</text>
<text id="74307007">%null%</text>
<text id="74307008">%null%</text>
<text id="74307009">%null%</text>
<text id="74307010">Huh huh, My dear friend, take these.</text>
<text id="74400000">Hello there. Travelling all alone in these treacherous times?</text>
<text id="74400001">%null%</text>
<text id="74400002">%null%</text>
<text id="74400003">%null%</text>
<text id="74400004">%null%</text>
<text id="74400005">%null%</text>
<text id="74400006">%null%</text>
<text id="74400007">%null%</text>
<text id="74400008">%null%</text>
<text id="74400009">%null%</text>
<text id="74400010">Well, I hope you have a very good reason.</text>
<text id="74400011">%null%</text>
<text id="74400012">%null%</text>
<text id="74400013">%null%</text>
<text id="74400014">%null%</text>
<text id="74400015">%null%</text>
<text id="74400016">%null%</text>
<text id="74400017">%null%</text>
<text id="74400018">%null%</text>
<text id="74400019">%null%</text>
<text id="74400020">Oh, hogwash, who am I to judge? Hah...</text>
<text id="74400021">%null%</text>
<text id="74400022">%null%</text>
<text id="74400023">%null%</text>
<text id="74400024">%null%</text>
<text id="74400025">%null%</text>
<text id="74400026">%null%</text>
<text id="74400027">%null%</text>
<text id="74400028">%null%</text>
<text id="74400029">%null%</text>
<text id="74400030">My name is Pate.</text>
<text id="74400031">%null%</text>
<text id="74400032">%null%</text>
<text id="74400033">%null%</text>
<text id="74400034">%null%</text>
<text id="74400035">%null%</text>
<text id="74400036">%null%</text>
<text id="74400037">%null%</text>
<text id="74400038">%null%</text>
<text id="74400039">%null%</text>
<text id="74400040">I journey hither and thither... On a sort of...
...treasure hunt, you might call it.</text>
<text id="74400041">%null%</text>
<text id="74400042">%null%</text>
<text id="74400043">%null%</text>
<text id="74400044">%null%</text>
<text id="74400045">%null%</text>
<text id="74400046">%null%</text>
<text id="74400047">%null%</text>
<text id="74400048">%null%</text>
<text id="74400049">%null%</text>
<text id="74400050">Be careful out there. There's talk of unsavoury bandits
who prey upon travellers like yourself.</text>
<text id="74400100">Oh yes, you be cautious
if you go any farther.</text>
<text id="74400101">%null%</text>
<text id="74400102">%null%</text>
<text id="74400103">%null%</text>
<text id="74400104">%null%</text>
<text id="74400105">%null%</text>
<text id="74400106">%null%</text>
<text id="74400107">%null%</text>
<text id="74400108">%null%</text>
<text id="74400109">%null%</text>
<text id="74400110">There's treasure in there, for certain,
but the entrance locks from behind.</text>
<text id="74400111">%null%</text>
<text id="74400112">%null%</text>
<text id="74400113">%null%</text>
<text id="74400114">%null%</text>
<text id="74400115">%null%</text>
<text id="74400116">%null%</text>
<text id="74400117">%null%</text>
<text id="74400118">%null%</text>
<text id="74400119">%null%</text>
<text id="74400120">I saw the same design earlier,
and it's the same contraption, I'm sure.</text>
<text id="74400121">%null%</text>
<text id="74400122">%null%</text>
<text id="74400123">%null%</text>
<text id="74400124">%null%</text>
<text id="74400125">%null%</text>
<text id="74400126">%null%</text>
<text id="74400127">%null%</text>
<text id="74400128">%null%</text>
<text id="74400129">%null%</text>
<text id="74400130">I was with this warrior, you see,
and he insisted that he go inside first.</text>
<text id="74400131">%null%</text>
<text id="74400132">%null%</text>
<text id="74400133">%null%</text>
<text id="74400134">%null%</text>
<text id="74400135">%null%</text>
<text id="74400136">%null%</text>
<text id="74400137">%null%</text>
<text id="74400138">%null%</text>
<text id="74400139">%null%</text>
<text id="74400140">The rather brusque fellow tried to swipe
the loot for himself, but it trapped him inside.</text>
<text id="74400141">%null%</text>
<text id="74400142">%null%</text>
<text id="74400143">%null%</text>
<text id="74400144">%null%</text>
<text id="74400145">%null%</text>
<text id="74400146">%null%</text>
<text id="74400147">%null%</text>
<text id="74400148">%null%</text>
<text id="74400149">%null%</text>
<text id="74400150">I still have the gent's ring.
I do hope he wasn't harmed.</text>
<text id="74400200">I'll leave this one to you.
I'm worried about what might be inside.</text>
<text id="74400300">Well, I see you managed to escape.</text>
<text id="74400301">%null%</text>
<text id="74400302">%null%</text>
<text id="74400303">%null%</text>
<text id="74400304">%null%</text>
<text id="74400305">%null%</text>
<text id="74400306">%null%</text>
<text id="74400307">%null%</text>
<text id="74400308">%null%</text>
<text id="74400309">%null%</text>
<text id="74400310">I hope that brave warrior didn't come a cropper either.</text>
<text id="74400311">%null%</text>
<text id="74400312">%null%</text>
<text id="74400313">%null%</text>
<text id="74400314">%null%</text>
<text id="74400315">%null%</text>
<text id="74400316">%null%</text>
<text id="74400317">%null%</text>
<text id="74400318">%null%</text>
<text id="74400319">%null%</text>
<text id="74400320">Be careful out there. There's talk of unsavoury bandits
who prey upon travellers like yourself.</text>
<text id="74400321">%null%</text>
<text id="74400322">%null%</text>
<text id="74400323">%null%</text>
<text id="74400324">%null%</text>
<text id="74400325">%null%</text>
<text id="74400326">%null%</text>
<text id="74400327">%null%</text>
<text id="74400328">%null%</text>
<text id="74400329">%null%</text>
<text id="74400330">There's a right foul creature lurking this way.
I'd say, why disturb the thing?</text>
<text id="74400331">%null%</text>
<text id="74400332">%null%</text>
<text id="74400333">%null%</text>
<text id="74400334">%null%</text>
<text id="74400335">%null%</text>
<text id="74400336">%null%</text>
<text id="74400337">%null%</text>
<text id="74400338">%null%</text>
<text id="74400339">%null%</text>
<text id="74400340">But if you must go on, I'm not one to stop you.</text>
<text id="74400341">%null%</text>
<text id="74400342">%null%</text>
<text id="74400343">%null%</text>
<text id="74400344">%null%</text>
<text id="74400345">%null%</text>
<text id="74400346">%null%</text>
<text id="74400347">%null%</text>
<text id="74400348">%null%</text>
<text id="74400349">%null%</text>
<text id="74400350">Oh, but you should take this.</text>
<text id="74400351">%null%</text>
<text id="74400352">%null%</text>
<text id="74400353">%null%</text>
<text id="74400354">%null%</text>
<text id="74400355">%null%</text>
<text id="74400356">%null%</text>
<text id="74400357">%null%</text>
<text id="74400358">%null%</text>
<text id="74400359">%null%</text>
<text id="74400360">It allows Undead to call out for help
to one another, across the fissures between worlds.</text>
<text id="74400361">%null%</text>
<text id="74400362">%null%</text>
<text id="74400363">%null%</text>
<text id="74400364">%null%</text>
<text id="74400365">%null%</text>
<text id="74400366">%null%</text>
<text id="74400367">%null%</text>
<text id="74400368">%null%</text>
<text id="74400369">%null%</text>
<text id="74400370">With luck, somebody will lend you a hand.</text>
<text id="74400371">%null%</text>
<text id="74400372">%null%</text>
<text id="74400373">%null%</text>
<text id="74400374">%null%</text>
<text id="74400375">%null%</text>
<text id="74400376">%null%</text>
<text id="74400377">%null%</text>
<text id="74400378">%null%</text>
<text id="74400379">%null%</text>
<text id="74400380">I wish I were more help myself,
but I haven't much bravery in me. Heh heh...</text>
<text id="74400500">Well, that was a close call! Heh heh...</text>
<text id="74400501">%null%</text>
<text id="74400502">%null%</text>
<text id="74400503">%null%</text>
<text id="74400504">%null%</text>
<text id="74400505">%null%</text>
<text id="74400506">%null%</text>
<text id="74400507">%null%</text>
<text id="74400508">%null%</text>
<text id="74400509">%null%</text>
<text id="74400510">I wanted to warn you of the trap down the way,
but you walked right past me.</text>
<text id="74400511">%null%</text>
<text id="74400512">%null%</text>
<text id="74400513">%null%</text>
<text id="74400514">%null%</text>
<text id="74400515">%null%</text>
<text id="74400516">%null%</text>
<text id="74400517">%null%</text>
<text id="74400518">%null%</text>
<text id="74400519">%null%</text>
<text id="74400520">My name is Pate.</text>
<text id="74400521">%null%</text>
<text id="74400522">%null%</text>
<text id="74400523">%null%</text>
<text id="74400524">%null%</text>
<text id="74400525">%null%</text>
<text id="74400526">%null%</text>
<text id="74400527">%null%</text>
<text id="74400528">%null%</text>
<text id="74400529">%null%</text>
<text id="74400530">I journey hither and thither...On a sort of...
...treasure hunt, you might call it.</text>
<text id="74400531">%null%</text>
<text id="74400532">%null%</text>
<text id="74400533">%null%</text>
<text id="74400534">%null%</text>
<text id="74400535">%null%</text>
<text id="74400536">%null%</text>
<text id="74400537">%null%</text>
<text id="74400538">%null%</text>
<text id="74400539">%null%</text>
<text id="74400540">Be careful out there. There's talk of unsavoury bandits
who prey upon travellers like yourself.</text>
<text id="74400700">Good to see you safe.</text>
<text id="74405000">Oh, I can scrimmage, my friend.</text>
<text id="74405001">%null%</text>
<text id="74405002">%null%</text>
<text id="74405003">%null%</text>
<text id="74405004">%null%</text>
<text id="74405005">%null%</text>
<text id="74405006">%null%</text>
<text id="74405007">%null%</text>
<text id="74405008">%null%</text>
<text id="74405009">%null%</text>
<text id="74405010">You again? Oh, heavens...</text>
<text id="74405011">%null%</text>
<text id="74405012">%null%</text>
<text id="74405013">%null%</text>
<text id="74405014">%null%</text>
<text id="74405015">%null%</text>
<text id="74405016">%null%</text>
<text id="74405017">%null%</text>
<text id="74405018">%null%</text>
<text id="74405019">%null%</text>
<text id="74405020">Heh heh heh...</text>
<text id="74405021">%null%</text>
<text id="74405022">%null%</text>
<text id="74405023">%null%</text>
<text id="74405024">%null%</text>
<text id="74405025">%null%</text>
<text id="74405026">%null%</text>
<text id="74405027">%null%</text>
<text id="74405028">%null%</text>
<text id="74405029">%null%</text>
<text id="74405030">Eek!</text>
<text id="74405031">%null%</text>
<text id="74405032">%null%</text>
<text id="74405033">%null%</text>
<text id="74405034">%null%</text>
<text id="74405035">%null%</text>
<text id="74405036">%null%</text>
<text id="74405037">%null%</text>
<text id="74405038">%null%</text>
<text id="74405039">%null%</text>
<text id="74405040">What the devil's...!</text>
<text id="74405041">%null%</text>
<text id="74405042">%null%</text>
<text id="74405043">%null%</text>
<text id="74405044">%null%</text>
<text id="74405045">%null%</text>
<text id="74405046">%null%</text>
<text id="74405047">%null%</text>
<text id="74405048">%null%</text>
<text id="74405049">%null%</text>
<text id="74405050">Now, stop that!</text>
<text id="74405051">%null%</text>
<text id="74405052">%null%</text>
<text id="74405053">%null%</text>
<text id="74405054">%null%</text>
<text id="74405055">%null%</text>
<text id="74405056">%null%</text>
<text id="74405057">%null%</text>
<text id="74405058">%null%</text>
<text id="74405059">%null%</text>
<text id="74405060">Not too shabby... Heh heh...</text>
<text id="74405061">%null%</text>
<text id="74405062">%null%</text>
<text id="74405063">%null%</text>
<text id="74405064">%null%</text>
<text id="74405065">%null%</text>
<text id="74405066">%null%</text>
<text id="74405067">%null%</text>
<text id="74405068">%null%</text>
<text id="74405069">%null%</text>
<text id="74405070">Aiieeegh!</text>
<text id="74406000">Heh heh heh...</text>
<text id="74407000">We went through a lot together.
Take these, as a token of our friendship.</text>
<text id="74407001">%null%</text>
<text id="74407002">%null%</text>
<text id="74407003">%null%</text>
<text id="74407004">%null%</text>
<text id="74407005">%null%</text>
<text id="74407006">%null%</text>
<text id="74407007">%null%</text>
<text id="74407008">%null%</text>
<text id="74407009">%null%</text>
<text id="74407010">Don't be shy, they were meant for you... Heh heh...</text>
<text id="75100000">Oh, I'm sorry.
I was just...daydreaming, I think.</text>
<text id="75100001">%null%</text>
<text id="75100002">%null%</text>
<text id="75100003">%null%</text>
<text id="75100004">%null%</text>
<text id="75100005">%null%</text>
<text id="75100006">%null%</text>
<text id="75100007">%null%</text>
<text id="75100008">%null%</text>
<text id="75100009">%null%</text>
<text id="75100010">My name is Cale.
I am a traveller, like yourself.</text>
<text id="75100011">%null%</text>
<text id="75100012">%null%</text>
<text id="75100013">%null%</text>
<text id="75100014">%null%</text>
<text id="75100015">%null%</text>
<text id="75100016">%null%</text>
<text id="75100017">%null%</text>
<text id="75100018">%null%</text>
<text id="75100019">%null%</text>
<text id="75100020">I'm navigating the continent to create a map.</text>
<text id="75100100">Why cartography, you ask?</text>
<text id="75100101">%null%</text>
<text id="75100102">%null%</text>
<text id="75100103">%null%</text>
<text id="75100104">%null%</text>
<text id="75100105">%null%</text>
<text id="75100106">%null%</text>
<text id="75100107">%null%</text>
<text id="75100108">%null%</text>
<text id="75100109">%null%</text>
<text id="75100110">Well...that's a good question...</text>
<text id="75100111">%null%</text>
<text id="75100112">%null%</text>
<text id="75100113">%null%</text>
<text id="75100114">%null%</text>
<text id="75100115">%null%</text>
<text id="75100116">%null%</text>
<text id="75100117">%null%</text>
<text id="75100118">%null%</text>
<text id="75100119">%null%</text>
<text id="75100120">When I first came to this forsaken land...</text>
<text id="75100121">%null%</text>
<text id="75100122">%null%</text>
<text id="75100123">%null%</text>
<text id="75100124">%null%</text>
<text id="75100125">%null%</text>
<text id="75100126">%null%</text>
<text id="75100127">%null%</text>
<text id="75100128">%null%</text>
<text id="75100129">%null%</text>
<text id="75100130">...It was...um...hmm...?</text>
<text id="75100131">%null%</text>
<text id="75100132">%null%</text>
<text id="75100133">%null%</text>
<text id="75100134">%null%</text>
<text id="75100135">%null%</text>
<text id="75100136">%null%</text>
<text id="75100137">%null%</text>
<text id="75100138">%null%</text>
<text id="75100139">%null%</text>
<text id="75100140">Err...a curse...?
Err...something about a curse...</text>
<text id="75100141">%null%</text>
<text id="75100142">%null%</text>
<text id="75100143">%null%</text>
<text id="75100144">%null%</text>
<text id="75100145">%null%</text>
<text id="75100146">%null%</text>
<text id="75100147">%null%</text>
<text id="75100148">%null%</text>
<text id="75100149">%null%</text>
<text id="75100150">Hah hah... How embarrasing. 
I seem to have lost my focus. </text>
<text id="75100151">%null%</text>
<text id="75100152">%null%</text>
<text id="75100153">%null%</text>
<text id="75100154">%null%</text>
<text id="75100155">%null%</text>
<text id="75100156">%null%</text>
<text id="75100157">%null%</text>
<text id="75100158">%null%</text>
<text id="75100159">%null%</text>
<text id="75100160">But I do know one thing for certain.
I have always been very fond of maps.</text>
<text id="75100200">I came to this land some time ago.</text>
<text id="75100201">%null%</text>
<text id="75100202">%null%</text>
<text id="75100203">%null%</text>
<text id="75100204">%null%</text>
<text id="75100205">%null%</text>
<text id="75100206">%null%</text>
<text id="75100207">%null%</text>
<text id="75100208">%null%</text>
<text id="75100209">%null%</text>
<text id="75100210">Drangleic, the lost kingdom...
It sounded so romantic...</text>
<text id="75100211">%null%</text>
<text id="75100212">%null%</text>
<text id="75100213">%null%</text>
<text id="75100214">%null%</text>
<text id="75100215">%null%</text>
<text id="75100216">%null%</text>
<text id="75100217">%null%</text>
<text id="75100218">%null%</text>
<text id="75100219">%null%</text>
<text id="75100220">Have you seen Majula?
There's a rather spacious mansion there.</text>
<text id="75100221">%null%</text>
<text id="75100222">%null%</text>
<text id="75100223">%null%</text>
<text id="75100224">%null%</text>
<text id="75100225">%null%</text>
<text id="75100226">%null%</text>
<text id="75100227">%null%</text>
<text id="75100228">%null%</text>
<text id="75100229">%null%</text>
<text id="75100230">I...I've made it my temporary home.
A...As something of a squatter, I'm afraid.</text>
<text id="75100300">Inside the mansion, I found a strange map.
Like none I'd ever seen.</text>
<text id="75100301">%null%</text>
<text id="75100302">%null%</text>
<text id="75100303">%null%</text>
<text id="75100304">%null%</text>
<text id="75100305">%null%</text>
<text id="75100306">%null%</text>
<text id="75100307">%null%</text>
<text id="75100308">%null%</text>
<text id="75100309">%null%</text>
<text id="75100310">I believe that it's a map of Drangleic.</text>
<text id="75100311">%null%</text>
<text id="75100312">%null%</text>
<text id="75100313">%null%</text>
<text id="75100314">%null%</text>
<text id="75100315">%null%</text>
<text id="75100316">%null%</text>
<text id="75100317">%null%</text>
<text id="75100318">%null%</text>
<text id="75100319">%null%</text>
<text id="75100320">Now I'm travelling the land to prove it.</text>
<text id="75100321">%null%</text>
<text id="75100322">%null%</text>
<text id="75100323">%null%</text>
<text id="75100324">%null%</text>
<text id="75100325">%null%</text>
<text id="75100326">%null%</text>
<text id="75100327">%null%</text>
<text id="75100328">%null%</text>
<text id="75100329">%null%</text>
<text id="75100330">Yes, yes, that's it!
That's why I came to the kingdom!</text>
<text id="75100331">%null%</text>
<text id="75100332">%null%</text>
<text id="75100333">%null%</text>
<text id="75100334">%null%</text>
<text id="75100335">%null%</text>
<text id="75100336">%null%</text>
<text id="75100337">%null%</text>
<text id="75100338">%null%</text>
<text id="75100339">%null%</text>
<text id="75100340">Wait...No, that wasn't it...</text>
<text id="75100341">%null%</text>
<text id="75100342">%null%</text>
<text id="75100343">%null%</text>
<text id="75100344">%null%</text>
<text id="75100345">%null%</text>
<text id="75100346">%null%</text>
<text id="75100347">%null%</text>
<text id="75100348">%null%</text>
<text id="75100349">%null%</text>
<text id="75100350">Then what? I don't seem to recall...</text>
<text id="75100400">Were you looking for that map?</text>
<text id="75100401">%null%</text>
<text id="75100402">%null%</text>
<text id="75100403">%null%</text>
<text id="75100404">%null%</text>
<text id="75100405">%null%</text>
<text id="75100406">%null%</text>
<text id="75100407">%null%</text>
<text id="75100408">%null%</text>
<text id="75100409">%null%</text>
<text id="75100410">Wonderful! Then you're fascinated
by maps, just like me?!</text>
<text id="75100411">%null%</text>
<text id="75100412">%null%</text>
<text id="75100413">%null%</text>
<text id="75100414">%null%</text>
<text id="75100415">%null%</text>
<text id="75100416">%null%</text>
<text id="75100417">%null%</text>
<text id="75100418">%null%</text>
<text id="75100419">%null%</text>
<text id="75100420">Shame on you,
you should have told me before!</text>
<text id="75100421">%null%</text>
<text id="75100422">%null%</text>
<text id="75100423">%null%</text>
<text id="75100424">%null%</text>
<text id="75100425">%null%</text>
<text id="75100426">%null%</text>
<text id="75100427">%null%</text>
<text id="75100428">%null%</text>
<text id="75100429">%null%</text>
<text id="75100430">Here, take this! A key to the mansion!</text>
<text id="75100431">%null%</text>
<text id="75100432">%null%</text>
<text id="75100433">%null%</text>
<text id="75100434">%null%</text>
<text id="75100435">%null%</text>
<text id="75100436">%null%</text>
<text id="75100437">%null%</text>
<text id="75100438">%null%</text>
<text id="75100439">%null%</text>
<text id="75100440">What a joy to meet a kindred spirit out here...</text>
<text id="75100500">Incredible really, isn't it? Such a map, to be chiselled in stone...</text>
<text id="75100501">%null%</text>
<text id="75100502">%null%</text>
<text id="75100503">%null%</text>
<text id="75100504">%null%</text>
<text id="75100505">%null%</text>
<text id="75100506">%null%</text>
<text id="75100507">%null%</text>
<text id="75100508">%null%</text>
<text id="75100509">%null%</text>
<text id="75100510">Oh, but one thing...</text>
<text id="75100511">%null%</text>
<text id="75100512">%null%</text>
<text id="75100513">%null%</text>
<text id="75100514">%null%</text>
<text id="75100515">%null%</text>
<text id="75100516">%null%</text>
<text id="75100517">%null%</text>
<text id="75100518">%null%</text>
<text id="75100519">%null%</text>
<text id="75100520">I would not venture deep into the mansion.</text>
<text id="75100521">%null%</text>
<text id="75100522">%null%</text>
<text id="75100523">%null%</text>
<text id="75100524">%null%</text>
<text id="75100525">%null%</text>
<text id="75100526">%null%</text>
<text id="75100527">%null%</text>
<text id="75100528">%null%</text>
<text id="75100529">%null%</text>
<text id="75100530">I can't be certain, but...
I've heard disturbing noises...</text>
<text id="75100531">%null%</text>
<text id="75100532">%null%</text>
<text id="75100533">%null%</text>
<text id="75100534">%null%</text>
<text id="75100535">%null%</text>
<text id="75100536">%null%</text>
<text id="75100537">%null%</text>
<text id="75100538">%null%</text>
<text id="75100539">%null%</text>
<text id="75100540">Something about it feels wrong...
Just be careful, please.</text>
<text id="75100600">I'll be back in Majula soon.</text>
<text id="75100601">%null%</text>
<text id="75100602">%null%</text>
<text id="75100603">%null%</text>
<text id="75100604">%null%</text>
<text id="75100605">%null%</text>
<text id="75100606">%null%</text>
<text id="75100607">%null%</text>
<text id="75100608">%null%</text>
<text id="75100609">%null%</text>
<text id="75100610">Perhaps we will meet again,
and discuss maps at our leisure!</text>
<text id="75105000">I shan't die here!</text>
<text id="75105001">%null%</text>
<text id="75105002">%null%</text>
<text id="75105003">%null%</text>
<text id="75105004">%null%</text>
<text id="75105005">%null%</text>
<text id="75105006">%null%</text>
<text id="75105007">%null%</text>
<text id="75105008">%null%</text>
<text id="75105009">%null%</text>
<text id="75105010">Shoo, go away!</text>
<text id="75105011">%null%</text>
<text id="75105012">%null%</text>
<text id="75105013">%null%</text>
<text id="75105014">%null%</text>
<text id="75105015">%null%</text>
<text id="75105016">%null%</text>
<text id="75105017">%null%</text>
<text id="75105018">%null%</text>
<text id="75105019">%null%</text>
<text id="75105020">Are you...all right?</text>
<text id="75105021">%null%</text>
<text id="75105022">%null%</text>
<text id="75105023">%null%</text>
<text id="75105024">%null%</text>
<text id="75105025">%null%</text>
<text id="75105026">%null%</text>
<text id="75105027">%null%</text>
<text id="75105028">%null%</text>
<text id="75105029">%null%</text>
<text id="75105030">Argh!</text>
<text id="75105031">%null%</text>
<text id="75105032">%null%</text>
<text id="75105033">%null%</text>
<text id="75105034">%null%</text>
<text id="75105035">%null%</text>
<text id="75105036">%null%</text>
<text id="75105037">%null%</text>
<text id="75105038">%null%</text>
<text id="75105039">%null%</text>
<text id="75105040">Watch it!</text>
<text id="75105041">%null%</text>
<text id="75105042">%null%</text>
<text id="75105043">%null%</text>
<text id="75105044">%null%</text>
<text id="75105045">%null%</text>
<text id="75105046">%null%</text>
<text id="75105047">%null%</text>
<text id="75105048">%null%</text>
<text id="75105049">%null%</text>
<text id="75105050">Stop that!</text>
<text id="75105051">%null%</text>
<text id="75105052">%null%</text>
<text id="75105053">%null%</text>
<text id="75105054">%null%</text>
<text id="75105055">%null%</text>
<text id="75105056">%null%</text>
<text id="75105057">%null%</text>
<text id="75105058">%null%</text>
<text id="75105059">%null%</text>
<text id="75105060">How could you!</text>
<text id="75105061">%null%</text>
<text id="75105062">%null%</text>
<text id="75105063">%null%</text>
<text id="75105064">%null%</text>
<text id="75105065">%null%</text>
<text id="75105066">%null%</text>
<text id="75105067">%null%</text>
<text id="75105068">%null%</text>
<text id="75105069">%null%</text>
<text id="75105070">My...my map...</text>
<text id="75106000">That map...It's spellbinding...</text>
<text id="75107000">Fate brought us together for a reason.</text>
<text id="75107001">%null%</text>
<text id="75107002">%null%</text>
<text id="75107003">%null%</text>
<text id="75107004">%null%</text>
<text id="75107005">%null%</text>
<text id="75107006">%null%</text>
<text id="75107007">%null%</text>
<text id="75107008">%null%</text>
<text id="75107009">%null%</text>
<text id="75107010">Take these. And may they help you on your travels.</text>
<text id="75400000">Buy something, anything... </text>
<text id="75400001">%null%</text>
<text id="75400002">%null%</text>
<text id="75400003">%null%</text>
<text id="75400004">%null%</text>
<text id="75400005">%null%</text>
<text id="75400006">%null%</text>
<text id="75400007">%null%</text>
<text id="75400008">%null%</text>
<text id="75400009">%null%</text>
<text id="75400010">Come, now...help an old woman...
And buy something...</text>
<text id="75400011">%null%</text>
<text id="75400012">%null%</text>
<text id="75400013">%null%</text>
<text id="75400014">%null%</text>
<text id="75400015">%null%</text>
<text id="75400016">%null%</text>
<text id="75400017">%null%</text>
<text id="75400018">%null%</text>
<text id="75400019">%null%</text>
<text id="75400020">Keh heh heh...</text>
<text id="75400200">Buy something, anything...</text>
<text id="75400300">Don't abandon a poor old woman...</text>
<text id="75400400">I knew you'd be back...</text>
<text id="75400500">You again? Keh heh heh...</text>
<text id="75400600">Thank you kindly. Keh heh heh...</text>
<text id="75400700">Lowly times, these are...</text>
<text id="75400800">Keh heh heh...</text>
<text id="75401000">My name is Melentia.</text>
<text id="75401001">%null%</text>
<text id="75401002">%null%</text>
<text id="75401003">%null%</text>
<text id="75401004">%null%</text>
<text id="75401005">%null%</text>
<text id="75401006">%null%</text>
<text id="75401007">%null%</text>
<text id="75401008">%null%</text>
<text id="75401009">%null%</text>
<text id="75401010">You a stranger to this land?</text>
<text id="75401011">%null%</text>
<text id="75401012">%null%</text>
<text id="75401013">%null%</text>
<text id="75401014">%null%</text>
<text id="75401015">%null%</text>
<text id="75401016">%null%</text>
<text id="75401017">%null%</text>
<text id="75401018">%null%</text>
<text id="75401019">%null%</text>
<text id="75401020">All we get is strangers these days.
Everybody's gone and run off! </text>
<text id="75401021">%null%</text>
<text id="75401022">%null%</text>
<text id="75401023">%null%</text>
<text id="75401024">%null%</text>
<text id="75401025">%null%</text>
<text id="75401026">%null%</text>
<text id="75401027">%null%</text>
<text id="75401028">%null%</text>
<text id="75401029">%null%</text>
<text id="75401030">Drangleic's been a pile o' rubble
since the war fought long, long ago.</text>
<text id="75401031">%null%</text>
<text id="75401032">%null%</text>
<text id="75401033">%null%</text>
<text id="75401034">%null%</text>
<text id="75401035">%null%</text>
<text id="75401036">%null%</text>
<text id="75401037">%null%</text>
<text id="75401038">%null%</text>
<text id="75401039">%null%</text>
<text id="75401040">When the Giants crossed the sea.</text>
<text id="75401100">Seemed like the battles would never end.</text>
<text id="75401101">%null%</text>
<text id="75401102">%null%</text>
<text id="75401103">%null%</text>
<text id="75401104">%null%</text>
<text id="75401105">%null%</text>
<text id="75401106">%null%</text>
<text id="75401107">%null%</text>
<text id="75401108">%null%</text>
<text id="75401109">%null%</text>
<text id="75401110">Poor folk like myself had nary a place to sleep.</text>
<text id="75401111">%null%</text>
<text id="75401112">%null%</text>
<text id="75401113">%null%</text>
<text id="75401114">%null%</text>
<text id="75401115">%null%</text>
<text id="75401116">%null%</text>
<text id="75401117">%null%</text>
<text id="75401118">%null%</text>
<text id="75401119">%null%</text>
<text id="75401120">That's why I keep all
me things right with me.</text>
<text id="75401121">%null%</text>
<text id="75401122">%null%</text>
<text id="75401123">%null%</text>
<text id="75401124">%null%</text>
<text id="75401125">%null%</text>
<text id="75401126">%null%</text>
<text id="75401127">%null%</text>
<text id="75401128">%null%</text>
<text id="75401129">%null%</text>
<text id="75401130">You may travel light, but methinks
you bear a burden of your own.</text>
<text id="75401200">They say these trees
grew from the remains of the Giants.</text>
<text id="75401201">%null%</text>
<text id="75401202">%null%</text>
<text id="75401203">%null%</text>
<text id="75401204">%null%</text>
<text id="75401205">%null%</text>
<text id="75401206">%null%</text>
<text id="75401207">%null%</text>
<text id="75401208">%null%</text>
<text id="75401209">%null%</text>
<text id="75401210">From each carcass sprouted new life,
growing into what you see now.</text>
<text id="75401211">%null%</text>
<text id="75401212">%null%</text>
<text id="75401213">%null%</text>
<text id="75401214">%null%</text>
<text id="75401215">%null%</text>
<text id="75401216">%null%</text>
<text id="75401217">%null%</text>
<text id="75401218">%null%</text>
<text id="75401219">%null%</text>
<text id="75401220">But you know what they also say.
Don't believe what an old hag says!</text>
<text id="75401300">It's high time that I pick up and move.</text>
<text id="75401301">%null%</text>
<text id="75401302">%null%</text>
<text id="75401303">%null%</text>
<text id="75401304">%null%</text>
<text id="75401305">%null%</text>
<text id="75401306">%null%</text>
<text id="75401307">%null%</text>
<text id="75401308">%null%</text>
<text id="75401309">%null%</text>
<text id="75401310">I've a bargain for you, next time we meet, my love. </text>
<text id="75405000">You've no respect! Die, you rotten lout!</text>
<text id="75405001">%null%</text>
<text id="75405002">%null%</text>
<text id="75405003">%null%</text>
<text id="75405004">%null%</text>
<text id="75405005">%null%</text>
<text id="75405006">%null%</text>
<text id="75405007">%null%</text>
<text id="75405008">%null%</text>
<text id="75405009">%null%</text>
<text id="75405010">I'll have your guts for garters! </text>
<text id="75405011">%null%</text>
<text id="75405012">%null%</text>
<text id="75405013">%null%</text>
<text id="75405014">%null%</text>
<text id="75405015">%null%</text>
<text id="75405016">%null%</text>
<text id="75405017">%null%</text>
<text id="75405018">%null%</text>
<text id="75405019">%null%</text>
<text id="75405020">Cruel, cruel world, this is... Keh heh heh...</text>
<text id="75405021">%null%</text>
<text id="75405022">%null%</text>
<text id="75405023">%null%</text>
<text id="75405024">%null%</text>
<text id="75405025">%null%</text>
<text id="75405026">%null%</text>
<text id="75405027">%null%</text>
<text id="75405028">%null%</text>
<text id="75405029">%null%</text>
<text id="75405030">Keh heh heh...</text>
<text id="75405031">%null%</text>
<text id="75405032">%null%</text>
<text id="75405033">%null%</text>
<text id="75405034">%null%</text>
<text id="75405035">%null%</text>
<text id="75405036">%null%</text>
<text id="75405037">%null%</text>
<text id="75405038">%null%</text>
<text id="75405039">%null%</text>
<text id="75405040">Keh heh heh...</text>
<text id="75405041">%null%</text>
<text id="75405042">%null%</text>
<text id="75405043">%null%</text>
<text id="75405044">%null%</text>
<text id="75405045">%null%</text>
<text id="75405046">%null%</text>
<text id="75405047">%null%</text>
<text id="75405048">%null%</text>
<text id="75405049">%null%</text>
<text id="75405050">%null%</text>
<text id="75405051">%null%</text>
<text id="75405052">%null%</text>
<text id="75405053">%null%</text>
<text id="75405054">%null%</text>
<text id="75405055">%null%</text>
<text id="75405056">%null%</text>
<text id="75405057">%null%</text>
<text id="75405058">%null%</text>
<text id="75405059">%null%</text>
<text id="75405060">That's not very nice, is it?</text>
<text id="75405061">%null%</text>
<text id="75405062">%null%</text>
<text id="75405063">%null%</text>
<text id="75405064">%null%</text>
<text id="75405065">%null%</text>
<text id="75405066">%null%</text>
<text id="75405067">%null%</text>
<text id="75405068">%null%</text>
<text id="75405069">%null%</text>
<text id="75405070">%null%</text>
<text id="75406000">Keh heh heh...</text>
<text id="75407000">Take these, if you want them. Keh heh heh...</text>
<text id="75407001">%null%</text>
<text id="75407002">%null%</text>
<text id="75407003">%null%</text>
<text id="75407004">%null%</text>
<text id="75407005">%null%</text>
<text id="75407006">%null%</text>
<text id="75407007">%null%</text>
<text id="75407008">%null%</text>
<text id="75407009">%null%</text>
<text id="75407010">Keh heh heh...</text>
</entries>
</fmg>